abadpour/README.py
abadpour/__init__.py
abadpour/__main__.py
abadpour/build.py
abadpour/logger.py
abadpour/urls.py
abadpour/.abcli/abadpour.sh
abadpour/.abcli/abcli.sh
abadpour/.abcli/actions.sh
abadpour/.abcli/build.sh
abadpour/.abcli/clean.sh
abadpour/.abcli/tests/build.sh
abadpour/.abcli/tests/help.sh
abadpour/.abcli/tests/version.sh
abadpour/help/__init_.py
abadpour/help/__main__.py
abadpour/help/functions.py
abadpour-7.18.1.dist-info/METADATA
abadpour-7.18.1.dist-info/WHEEL
abadpour-7.18.1.dist-info/top_level.txt
abadpour-7.18.1.dist-info/RECORD
