Metadata-Version: 2.4
Name: abadpour
Version: 7.18.1
Summary: 📜 Arash Abadpour's CV.
Home-page: https://github.com/kamangir/abadpour
Author: Arash Abadpour (Kamangir)
Author-email: arash.abadpour@gmail.com
License: CC0-1.0
Classifier: Programming Language :: Python :: 3
Classifier: Programming Language :: Unix Shell
Classifier: Operating System :: OS Independent
Requires-Dist: bluer_ai
Dynamic: author
Dynamic: author-email
Dynamic: classifier
Dynamic: description
Dynamic: description-content-type
Dynamic: home-page
Dynamic: license
Dynamic: requires-dist
Dynamic: summary
